{
	"bccvl_metadata_version": "2014-09-09-01",
	"title": "Vegetation Assets, States and Transitions",
	"genre": "Environmental",
	"data_type": "Categorical",
	"format": "GeoTIFF",
	"resolution": "30 arcsec",
	"geogcs": "WGS84",
	"bounding_box": {
		"top": "-10.0000000",
		"right": "154.0000000",
		"bottom": "-45.0000000",
		"left": "132.0000000"
	},
	"temporal_coverage": {
		"start": "2008",
		"end": "2008"
	},
        "files": {
		"vast/data/vastgridv2_1k.tif": {"layer": "vastgridv2_1k"}
        },
	"external_url": "http://data.daff.gov.au/anrdl/metadata_files/pa_vast_g9abll0032008_11a.xml",
	"license": "CC_BY_30_AU, Content supplied by third-parties is excluded from this license.",
	"acknowledgement": "All visual and pubished material must acknowledge the Australian Bureau of Agricultural and Resource Economics and Sciences (ABRES) compiled and derived the dataset."
}
